[
    {
      "id": 0,
      "campaignID": 11136,
      "wellnessName": "Parkhotel Horst",
      "title": "Parkhotel Horst",
      "url": "https://lt45.net/c/?si=11136&li=1500380&wi=244044&pid=fa547154ab6117a0ea55a9a45e9dc94c&dl=limburg%2Fparkhotel-horst&ws=",
      "oldPrice": 159,
      "newPrice": 143.1,
      "discount": 10,
      "image": "https://www.spaonline.com/spafotos/201/thumb/2.jpg",
      "location": "Horst|Limburg"
    },
    {
      "id": 1,
      "campaignID": 11136,
      "wellnessName": "Wellness Center De Bronsbergen",
      "title": "Wellness Center NLG de Bronsbergen",
      "url": "https://lt45.net/c/?si=11136&li=1500380&wi=244044&pid=43ddd8c13ed00195cae3c20760fc93d5&dl=gelderland%2Fsauna-bronsbergen-zutphen&ws=",
      "oldPrice": 41.5,
      "newPrice": 33.5,
      "discount": 19,
      "image": "https://www.spaonline.com/spafotos/286/thumb/1.jpg",
      "location": "Zutphen|Gelderland"
    },
    {
      "id": 2,
      "campaignID": 11136,
      "wellnessName": "Wellness Goes",
      "title": "Wellnessresort Goes",
      "url": "https://lt45.net/c/?si=11136&li=1500380&wi=244044&pid=9c655e6dfe292608d6887e6127b36903&dl=zeeland%2Fwellness-goes&ws=",
      "oldPrice": 30.5,
      "newPrice": 22.88,
      "discount": 25,
      "image": "https://www.spaonline.com/spafotos/214/thumb/1.jpg",
      "location": "Goes|Zeeland"
    },
    {
      "id": 3,
      "campaignID": 11136,
      "wellnessName": "Thermae Son",
      "title": "Thermae Son",
      "url": "https://lt45.net/c/?si=11136&li=1500380&wi=244044&pid=2298c195cac162984053a7a30f372a1a&dl=noord-brabant%2Fthermae-son&ws=",
      "oldPrice": 34,
      "newPrice": 30.6,
      "discount": 10,
      "image": "https://www.spaonline.com/spafotos/112/thumb/1.jpg",
      "location": "Son en Breugel|Noord-Brabant"
    },
    {
      "id": 4,
      "campaignID": 11136,
      "wellnessName": "Spavarin",
      "title": "Spavarin",
      "url": "https://lt45.net/c/?si=11136&li=1500380&wi=244044&pid=21cc58983803b178d2a4e89834e3a937&dl=zuid-holland%2Fspavarin&ws=",
      "oldPrice": 25,
      "newPrice": 22.5,
      "discount": 10,
      "image": "https://www.spaonline.com/spafotos/215/thumb/1.jpg",
      "location": "Rijswijk|Zuid-Holland"
    },
    {
      "id": 5,
      "campaignID": 11136,
      "wellnessName": "Sauna Beautyfarm Midwolda",
      "title": "Sauna Beauty Farm Midwolda",
      "url": "https://lt45.net/c/?si=11136&li=1500380&wi=244044&pid=635881ca3b3a4fcc4665452c5935b121&dl=groningen%2Fsauna-beauty-farm-midwolda&ws=",
      "oldPrice": 26.5,
      "newPrice": 23.85,
      "discount": 10,
      "image": "https://www.spaonline.com/spafotos/50/thumb/sbfarm.jpg",
      "location": "Midwolda|Groningen"
    },
    {
      "id": 6,
      "campaignID": 11136,
      "wellnessName": "Sauna En Beauty Ommen",
      "title": "Sauna & Beauty Ommen",
      "url": "https://lt45.net/c/?si=11136&li=1500380&wi=244044&pid=768d34d03649f0961d0fe337c8d73988&dl=overijssel%2Fsauna-beauty-ommen&ws=",
      "oldPrice": 22.5,
      "newPrice": 19,
      "discount": 16,
      "image": "https://www.spaonline.com/spafotos/76/thumb/1.jpg",
      "location": "Ommen|Overijssel"
    },
    {
      "id": 7,
      "campaignID": 11136,
      "wellnessName": "Sauna Epe",
      "title": "Saunapark Epe",
      "url": "https://lt45.net/c/?si=11136&li=1500380&wi=244044&pid=47e957843c634d53657245c8f04fe0c2&dl=overijssel%2Fsaunapark-epe&ws=",
      "oldPrice": 29.5,
      "newPrice": 26.55,
      "discount": 10,
      "image": "https://www.spaonline.com/spafotos/232/thumb/1.jpg",
      "location": "Gronau-Epe /Duitsland|Overijssel"
    },
    {
      "id": 8,
      "campaignID": 4179,
      "wellnessName": "Zwaluwhoeve",
      "title": "Zwaluwhoeve in Hierden, Gelderland: dagentree",
      "url": "https://tc.tradetracker.net/?c=4179&m=1185051&a=228134&r=&u=https%3A%2F%2Fwww.vakantieveilingen.nl%2Fveilingen%2Fsauna-en-beauty%2Fsauna-en-wellness%2Fzwaluwhoeve-sauna%2F32874",
      "oldPrice": null,
      "newPrice": 1,
      "discount": null,
      "image": "https://images.emesa-static.com/od-GJwGPPHlh_2upbxunvj8CfnY=/500x500/vv/images/products/442/153442/zwaluwhoeve-5-e18de209.jpg",
      "location": ["Hierden"]
    },
    {
      "id": 9,
      "campaignID": 4179,
      "wellnessName": "Veluwse Bron",
      "title": "Veluwse Bron in Emst, Gelderland: dagentree",
      "url": "https://tc.tradetracker.net/?c=4179&m=1185051&a=228134&r=&u=https%3A%2F%2Fwww.vakantieveilingen.nl%2Fveilingen%2Fsauna-en-beauty%2Fsauna-en-wellness%2Fveluwse-bron-2022%2F33409",
      "oldPrice": null,
      "newPrice": 1,
      "discount": null,
      "image": "https://images.emesa-static.com/rALeBv3iHSlhgiOOu_o5E1cwyYI=/500x500/vv/images/products/466/153466/veluwse-bron-4-63b48e09.jpg",
      "location": ["Emst"]
    },
    {
      "id": 10,
      "campaignID": 4179,
      "wellnessName": "Thermen Holiday",
      "title": "Thermen Holiday in Schiedam, Zuid-Holland: entree",
      "url": "https://tc.tradetracker.net/?c=4179&m=1185051&a=228134&r=&u=https%3A%2F%2Fwww.vakantieveilingen.nl%2Fveilingen%2Fsauna-en-beauty%2Fsauna-en-wellness%2Fthermen-holiday-sauna%2F33871",
      "oldPrice": null,
      "newPrice": 1,
      "discount": null,
      "image": "https://images.emesa-static.com/qpVckGvFZkTi7mpttwqP6L6Hi68=/500x500/vv/images/products/601/153601/thermen-holiday-4-9cf5569a.jpg",
      "location": ["Schiedam"]
    },
    {
      "id": 11,
      "campaignID": 4179,
      "wellnessName": "Elysium",
      "title": "Elysium in Bleiswijk, Zuid-Holland: dagentree",
      "url": "https://tc.tradetracker.net/?c=4179&m=1185051&a=228134&r=&u=https%3A%2F%2Fwww.vakantieveilingen.nl%2Fveilingen%2Fsauna-en-beauty%2Fsauna-en-wellness%2Fdagentree-sauna-wellnessresort-elysium%2F2229",
      "oldPrice": null,
      "newPrice": 1,
      "discount": null,
      "image": "https://images.emesa-static.com/k9T3qoTYlu1FMiZwvJL-zCBakto=/500x500/vv/images/products/399/153399/elysium-sauna-3-c09e4096.jpg",
      "location": ["Bleiswijk"]
    },
    {
      "id": 12,
      "campaignID": 4179,
      "wellnessName": "Wellnessboot Mill",
      "title": "Dagentree op BLUE Wellnessboot Mill, Brabant",
      "url": "https://tc.tradetracker.net/?c=4179&m=1185051&a=228134&r=&u=https%3A%2F%2Fwww.vakantieveilingen.nl%2Fveilingen%2Fsauna-en-beauty%2Fsauna-en-wellness%2Fblue-wellnessboot-mill-brabant%2F44391",
      "oldPrice": null,
      "newPrice": 1,
      "discount": null,
      "image": "https://images.emesa-static.com/bmiXT-VYolTvFW7_v28OTb9H1Jo=/500x500/vv/images/products/815/159815/blue_wellness_boot-0d2a397a.jpg",
      "location": []
    },
    {
      "id": 13,
      "campaignID": 4179,
      "wellnessName": "Wellness Helmond",
      "title": "Saunaentree bij BLUE Wellnessresort, Helmond",
      "url": "https://tc.tradetracker.net/?c=4179&m=1185051&a=228134&r=&u=https%3A%2F%2Fwww.vakantieveilingen.nl%2Fveilingen%2Fsauna-en-beauty%2Fsauna-en-wellness%2Fblue-wellnessresort-helmond%2F44394",
      "oldPrice": null,
      "newPrice": 1,
      "discount": null,
      "image": "https://images.emesa-static.com/NjxluUHCJFCfFvpcvk-EsirYRMI=/500x500/vv/images/products/818/159818/blue-wellness-helmond-1-8aa6d4cc.jpg",
      "location": []
    },
    {
      "id": 14,
      "campaignID": 4179,
      "wellnessName": "Wellness Sittard",
      "title": "Dagentree bij BLUE Wellnessresort Sittard",
      "url": "https://tc.tradetracker.net/?c=4179&m=1185051&a=228134&r=&u=https%3A%2F%2Fwww.vakantieveilingen.nl%2Fveilingen%2Fsauna-en-beauty%2Fsauna-en-wellness%2Fblue-wellnessresort-sittard%2F44393",
      "oldPrice": null,
      "newPrice": 1,
      "discount": null,
      "image": "https://images.emesa-static.com/HMz8i0hDl4B1qGeOvdGprmjwuz0=/500x500/vv/images/products/819/159819/blue-wellness-sittard-4-9d0efde4.jpg",
      "location": []
    },
    {
      "id": 15,
      "campaignID": 4179,
      "wellnessName": "Thermen De Waterlelie",
      "title": "Wellnessresort de Waterlelie: dag- of avondentree",
      "url": "https://tc.tradetracker.net/?c=4179&m=1185051&a=228134&r=&u=https%3A%2F%2Fwww.vakantieveilingen.nl%2Fveilingen%2Fsauna-en-beauty%2Fsauna-en-wellness%2Fwellnessresort-waterlelie-dagentree-of-avondentree%2F43711",
      "oldPrice": null,
      "newPrice": 1,
      "discount": null,
      "image": "https://images.emesa-static.com/X0QnmTIbdljQ-uen-fE8BSj0Dkc=/500x500/vv/images/products/294/159294/waterlelie-thermen-4-b377e211.jpg",
      "location": []
    },
    {
      "id": 16,
      "campaignID": 4179,
      "wellnessName": "Wellness Leiden",
      "title": "Dagentree bij BLUE Wellnessresort Leiden",
      "url": "https://tc.tradetracker.net/?c=4179&m=1185051&a=228134&r=&u=https%3A%2F%2Fwww.vakantieveilingen.nl%2Fveilingen%2Fsauna-en-beauty%2Fsauna-en-wellness%2Fblue-wellnessresort-leiden%2F44389",
      "oldPrice": null,
      "newPrice": 1,
      "discount": null,
      "image": "https://images.emesa-static.com/HrDB57RVFIbHaaKzzHOQyaQpeWk=/500x500/vv/images/products/816/159816/blue-wellness-leiden-1-f1ac6afc.jpg",
      "location": []
    },
    {
      "id": 17,
      "campaignID": 8308,
      "wellnessName": "Thermen Anholts",
      "title": "1 ticket voor Thermen & Wellness Anholts in Schoonebeek!",
      "url": "https://www.ticketveiling.nl/tickets/?tt=8308_1922718_228134_&r=https%3A%2F%2Fwww.ticketveiling.nl%2Fsauna%2Fsauna%2Fthermen-wellness-anholts-schoonebeek-korting-2",
      "oldPrice": null,
      "newPrice": 0,
      "discount": null,
      "image": "https://ticketveiling.imgix.net/aanbieders/Thermen-Anholts/Anholts-2-logo.jpg?q=70&w=560&h=300&fit=crop&auto=compress,format,enhance"
    },
    {
      "id": 18,
      "campaignID": 8308,
      "wellnessName": "Sauna Het Friese Woud",
      "title": "Een dagje ontspannen bij Sauna Het Friese Woud voor 2 personen!",
      "url": "https://www.ticketveiling.nl/tickets/?tt=8308_1922718_228134_&r=https%3A%2F%2Fwww.ticketveiling.nl%2Fsauna%2Fsauna%2Fsauna-het-friese-woud-2-personen-korting",
      "oldPrice": null,
      "newPrice": 0,
      "discount": null,
      "image": "https://ticketveiling.imgix.net/aanbieders/Het Friese Woud/Het-Friese-Woud-1-logo.jpg?q=70&w=560&h=300&fit=crop&auto=compress,format,enhance"
    },
    {
      "id": 19,
      "campaignID": 8308,
      "wellnessName": "Dennenmarken",
      "title": "Een dagje ontspannen bij Sauna Dennenmarken in Limburg!",
      "url": "https://www.ticketveiling.nl/tickets/?tt=8308_1922718_228134_&r=https%3A%2F%2Fwww.ticketveiling.nl%2Fsauna%2Fsauna%2Fsauna-dennenmarken-limburg-korting",
      "oldPrice": null,
      "newPrice": 0,
      "discount": null,
      "image": "https://ticketveiling.imgix.net/aanbieders/Dennenmarken-Sauna/Sauna-Dennenmarken-11689258364.jpg?q=70&w=560&h=300&fit=crop&auto=compress,format,enhance"
    },
    {
      "id": 20,
      "campaignID": 8308,
      "wellnessName": "Dennenmarken",
      "title": "Voor 2 personen een Wellness Hotelarrangement bij Sauna Dennenmarken!",
      "url": "https://www.ticketveiling.nl/tickets/?tt=8308_1922718_228134_&r=https%3A%2F%2Fwww.ticketveiling.nl%2Fhotels%2Fweekendjes-weg%2Fwellness-hotelarrangement-sauna-dennenmarken-korting",
      "oldPrice": null,
      "newPrice": 0,
      "discount": null,
      "image": "https://ticketveiling.imgix.net/aanbieders/Dennenmarken-Sauna/Overnachting-Dennenmarken-1.jpg?q=70&w=560&h=300&fit=crop&auto=compress,format,enhance"
    },
    {
      "id": 21,
      "campaignID": 8308,
      "title": "2x Dagentree + beautybehandeling + glaasje bubbels bij Sauna Dennenmarken!",
      "url": "https://www.ticketveiling.nl/tickets/?tt=8308_1922718_228134_&r=https%3A%2F%2Fwww.ticketveiling.nl%2Fsauna%2Fwellness-arrangementen%2Fsauna-dennenmarken-beautybehandeling-bubbels",
      "oldPrice": null,
      "newPrice": 0,
      "discount": null,
      "image": "https://ticketveiling.imgix.net/aanbieders/Dennenmarken-Sauna/Beautybehandeling-1.jpg?q=70&w=560&h=300&fit=crop&auto=compress,format,enhance"
    },
    {
      "id": 22,
      "campaignID": 8308,
      "wellnessName": "Sauna Drome Putten",
      "title": "2 avond entreetickets voor Sauna Drôme in Putten!",
      "url": "https://www.ticketveiling.nl/tickets/?tt=8308_1922718_228134_&r=https%3A%2F%2Fwww.ticketveiling.nl%2Fsauna%2Fsauna%2Fsaunadrome-putten-avondentree",
      "oldPrice": null,
      "newPrice": 0,
      "discount": null,
      "image": "https://ticketveiling.imgix.net/aanbieders/Saunadrome Putten/Sauna-Drome-1-logo.jpg?q=70&w=560&h=300&fit=crop&auto=compress,format,enhance"
    },
    {
      "id": 23,
      "campaignID": 8308,
      "wellnessName": "Sauna Het Friese Woud",
      "title": "Voor 1 persoon een dagje ontspannen bij Sauna Het Friese Woud!",
      "url": "https://www.ticketveiling.nl/tickets/?tt=8308_1922718_228134_&r=https%3A%2F%2Fwww.ticketveiling.nl%2Fsauna%2Fsauna%2Fsauna-het-friese-woud-korting",
      "oldPrice": null,
      "newPrice": 0,
      "discount": null,
      "image": "https://ticketveiling.imgix.net/aanbieders/Het Friese Woud/Friese-Woud-2-logo.jpg?q=70&w=560&h=300&fit=crop&auto=compress,format,enhance"
    },
    {
      "id": 24,
      "campaignID": 8308,
      "wellnessName": "Thermen Anholts",
      "title": "2 tickets voor Thermen & Wellness Anholts in Schoonebeek!",
      "url": "https://www.ticketveiling.nl/tickets/?tt=8308_1922718_228134_&r=https%3A%2F%2Fwww.ticketveiling.nl%2Fsauna%2Fsauna%2Fthermen-wellness-anholts-schoonebeek-korting",
      "oldPrice": null,
      "newPrice": 0,
      "discount": null,
      "image": "https://ticketveiling.imgix.net/aanbieders/Thermen-Anholts/Anholts-1-logo.jpg?q=70&w=560&h=300&fit=crop&auto=compress,format,enhance"
    },
    {
      "id": 25,
      "campaignID": 8308,
      "wellnessName": "Sauna Drome Putten",
      "title": "2 dagtickets voor Sauna Drôme in Putten!",
      "url": "https://www.ticketveiling.nl/tickets/?tt=8308_1922718_228134_&r=https%3A%2F%2Fwww.ticketveiling.nl%2Fsauna%2Fsauna%2Fsaunadrome-putten-dagentree-korting",
      "oldPrice": null,
      "newPrice": 0,
      "discount": null,
      "image": "https://ticketveiling.imgix.net/aanbieders/Saunadrome Putten/Saunadrome-logo.jpg?q=70&w=560&h=300&fit=crop&auto=compress,format,enhance"
    },
    {
      "id": 26,
      "campaignID": 8308,
      "wellnessName": "Spasereen",
      "title": "Voor 2 personen ontspannen bij SpaSereen in Maastricht!",
      "url": "https://www.ticketveiling.nl/tickets/?tt=8308_1922718_228134_&r=https%3A%2F%2Fwww.ticketveiling.nl%2Fsauna%2Fsauna%2Fspasereen-maastricht-korting",
      "oldPrice": null,
      "newPrice": 0,
      "discount": null,
      "image": "https://ticketveiling.imgix.net/Logo_Juni_2023/spasereen1.jpg?q=70&w=560&h=300&fit=crop&auto=compress,format,enhance"
    },
    {
      "id": 27,
      "campaignID": 8308,
      "wellnessName": "Sauna De Bron",
      "title": "Een heerlijk dagje ontspannen bij Sauna de Bron voor 2 personen!",
      "url": "https://www.ticketveiling.nl/tickets/?tt=8308_1922718_228134_&r=https%3A%2F%2Fwww.ticketveiling.nl%2Fsauna%2Fsauna%2Fsauna-de-bron-korting",
      "oldPrice": null,
      "newPrice": 0,
      "discount": null,
      "image": "https://ticketveiling.imgix.net/aanbieders/Sauna-de-Bron/Sauna-de-Bron-21689325018.jpg?q=70&w=560&h=300&fit=crop&auto=compress,format,enhance"
    },
    {
      "id": 28,
      "campaignID": 8308,
      "wellnessName": "Dennenmarken",
      "title": "Voor 2 personen sauna entree en 1 uur padellen bij Sauna Dennenmarken!",
      "url": "https://www.ticketveiling.nl/tickets/?tt=8308_1922718_228134_&r=https%3A%2F%2Fwww.ticketveiling.nl%2Fsauna%2Fsauna-entree-padellen-sauna-dennenmarken-korting",
      "oldPrice": null,
      "newPrice": 0,
      "discount": null,
      "image": "https://ticketveiling.imgix.net/aanbieders/Dennenmarken-Sauna/Sauna-Dennenmarken-Padel-1-logo.jpg?q=70&w=560&h=300&fit=crop&auto=compress,format,enhance"
    },
    {
      "id": 29,
      "campaignID": 8308,
      "wellnessName": "Centre Du Lac",
      "title": "2 tickets voor een heerlijke saunadag bij Centre du Lac!",
      "url": "https://www.ticketveiling.nl/tickets/?tt=8308_1922718_228134_&r=https%3A%2F%2Fwww.ticketveiling.nl%2Fsauna%2Fsauna%2Fcentre-du-lac-dagentree-korting",
      "oldPrice": null,
      "newPrice": 0,
      "discount": null,
      "image": "https://ticketveiling.imgix.net/Logo-januari-2023/centredulac2.jpg?q=70&w=560&h=300&fit=crop&auto=compress,format,enhance"
    },
    {
      "id": 30,
      "campaignID": 8308,
      "wellnessName": "Sauna Drome Putten",
      "title": "1 avond entreeticket voor Sauna Drôme in Putten!",
      "url": "https://www.ticketveiling.nl/tickets/?tt=8308_1922718_228134_&r=https%3A%2F%2Fwww.ticketveiling.nl%2Fsauna%2Fsauna%2Fsaunadrome-putten-avondentree-1persoon",
      "oldPrice": null,
      "newPrice": 0,
      "discount": null,
      "image": "https://ticketveiling.imgix.net/aanbieders/Saunadrome Putten/Saunadrome-logo-4.jpg?q=70&w=560&h=300&fit=crop&auto=compress,format,enhance"
    },
    {
      "id": 31,
      "campaignID": 8308,
      "title": "1 dagticket voor Sauna Drôme in Putten!",
      "url": "https://www.ticketveiling.nl/tickets/?tt=8308_1922718_228134_&r=https%3A%2F%2Fwww.ticketveiling.nl%2Fsauna%2Fsauna%2Fsaunadrome-putten-dagentree-1",
      "oldPrice": null,
      "newPrice": 0,
      "discount": null,
      "image": "https://ticketveiling.imgix.net/aanbieders/Saunadrome Putten/Sauna-Drome-22.jpg?q=70&w=560&h=300&fit=crop&auto=compress,format,enhance"
    },
    {
      "id": 32,
      "campaignID": 8308,
      "wellnessName": "Centre Du Lac",
      "title": "Een heerlijk ontspannen saunadag bij Centre du Lac voor 1 persoon!",
      "url": "https://www.ticketveiling.nl/tickets/?tt=8308_1922718_228134_&r=https%3A%2F%2Fwww.ticketveiling.nl%2Fsauna%2Fsauna%2Fsauna-centredulac-korting",
      "oldPrice": null,
      "newPrice": 0,
      "discount": null,
      "image": "https://ticketveiling.imgix.net/Logo-januari-2023/centredulac.jpg?q=70&w=560&h=300&fit=crop&auto=compress,format,enhance"
    },
    {
      "id": 33,
      "campaignID": 8308,
      "wellnessName": "Thermen De Waterlelie",
      "title": "2 tickets voor Wellnessresort de Waterlelie!",
      "url": "https://www.ticketveiling.nl/tickets/?tt=8308_1922718_228134_&r=https%3A%2F%2Fwww.ticketveiling.nl%2Fsauna%2Fsauna%2Fwellnessresort-de-waterlelie-korting",
      "oldPrice": null,
      "newPrice": 0,
      "discount": null,
      "image": "https://ticketveiling.imgix.net/aanbieders/Wellnessresort-Waterlelie/Waterlelie.jpg?q=70&w=560&h=300&fit=crop&auto=compress,format,enhance"
    },
    {
      "id": 34,
      "campaignID": 26224,
      "wellnessName": "Sauna De Bron",
      "title": "Entree Sauna de Bron",
      "url": "https://www.tripper.nl/trips/?tt=26224_1169772_228134_&r=https%3A%2F%2Fwww.tripper.nl%2Fdeal%2Fdagentree-sauna-de-bron-korting",
      "oldPrice": 31.95,
      "newPrice": 20.5,
      "discount": 36,
      "image": "https://tripper.imgix.net/dagentree-sauna-de-bron-korting/8e45d1.jpg"
    },
    {
      "id": 35,
      "campaignID": 26224,
      "wellnessName": "Dennenmarken",
      "title": "Entreeticket Sauna Dennenmarken",
      "url": "https://www.tripper.nl/trips/?tt=26224_1169772_228134_&r=https%3A%2F%2Fwww.tripper.nl%2Fdeal%2Fentree-sauna-dennenmarken-korting",
      "oldPrice": 38.5,
      "newPrice": 20.5,
      "discount": 47,
      "image": "https://tripper.imgix.net/entree-sauna-dennenmarken-korting/70b1be.jpg"
    },
    {
      "id": 36,
      "campaignID": 26224,
      "wellnessName": "Spasereen",
      "title": "Entreeticket SpaSereen Maastricht",
      "url": "https://www.tripper.nl/trips/?tt=26224_1169772_228134_&r=https%3A%2F%2Fwww.tripper.nl%2Fdeal%2Fticket-spasereen-maastricht-korting",
      "oldPrice": 39.5,
      "newPrice": 29.5,
      "discount": 25,
      "image": "https://tripper.imgix.net/ticket-spasereen-maastricht-korting/794c92.jpg"
    },
    {
      "id": 37,
      "campaignID": 26224,
      "wellnessName": "Sauna Drome Putten",
      "title": "Dag of avondentree Sauna Drôme in Putten",
      "url": "https://www.tripper.nl/trips/?tt=26224_1169772_228134_&r=https%3A%2F%2Fwww.tripper.nl%2Fdeal%2Ftickets-sauna-drome-putten-korting",
      "oldPrice": 35.5,
      "newPrice": 21.5,
      "discount": 39,
      "image": "https://tripper.imgix.net/tickets-sauna-drome-putten-korting/e38cb6.jpg"
    },
    {
      "id": 38,
      "campaignID": 26224,
      "wellnessName": "Dennenmarken",
      "title": "Entree Sauna Dennenmarken + behandeling/drankje of maaltijdsalade",
      "url": "https://www.tripper.nl/trips/?tt=26224_1169772_228134_&r=https%3A%2F%2Fwww.tripper.nl%2Fdeal%2Fentree-sauna-dennenmarken-arrangementen-korting",
      "oldPrice": 63.5,
      "newPrice": 36.5,
      "discount": 43,
      "image": "https://tripper.imgix.net/entree-sauna-dennenmarken-arrangementen-korting/e3101e.jpg"
    },
    {
      "id": 39,
      "campaignID": 26224,
      "wellnessName": "Sauna Het Friese Woud",
      "title": "Dagentree Sauna Het Friese Woud",
      "url": "https://www.tripper.nl/trips/?tt=26224_1169772_228134_&r=https%3A%2F%2Fwww.tripper.nl%2Fdeal%2Fsauna-friese-woud-met-korting",
      "oldPrice": 29.5,
      "newPrice": 23.5,
      "discount": 20,
      "image": "https://tripper.imgix.net/sauna-friese-woud-met-korting/a59baf.jpg"
    },
    {
      "id": 40,
      "campaignID": 26224,
      "wellnessName": "Thermen Anholts",
      "title": "Entreeticket Thermen & Beautycentrum Anholts",
      "url": "https://www.tripper.nl/trips/?tt=26224_1169772_228134_&r=https%3A%2F%2Fwww.tripper.nl%2Fdeal%2Fticket-thermen-beautycentrum-anholts-korting",
      "oldPrice": 33,
      "newPrice": 25.5,
      "discount": 23,
      "image": "https://tripper.imgix.net/ticket-thermen-beautycentrum-anholts-korting/1c7997.jpg"
    },
    {
      "id": 41,
      "campaignID": 26224,
      "wellnessName": "Thermen De Waterlelie",
      "title": "Dagentree Wellnessresort de Waterlelie",
      "url": "https://www.tripper.nl/trips/?tt=26224_1169772_228134_&r=https%3A%2F%2Fwww.tripper.nl%2Fdeal%2Fkorting-dagentree-wellnessresort-de-waterlelie-korting",
      "oldPrice": 39.5,
      "newPrice": 25.95,
      "discount": 34,
      "image": "https://tripper.imgix.net/korting-dagentree-wellnessresort-de-waterlelie-korting/43beec.jpg"
    },
    {
      "id": 42,
      "campaignID": 26224,
      "wellnessName": "Dennenmarken",
      "title": "Entree Sauna Dennenmarken + 1 uur Padel",
      "url": "https://www.tripper.nl/trips/?tt=26224_1169772_228134_&r=https%3A%2F%2Fwww.tripper.nl%2Fdeal%2Fentree-sauna-dennenmarken-1-uur-padel-korting",
      "oldPrice": 31.5,
      "newPrice": 19,
      "discount": 40,
      "image": "https://tripper.imgix.net/entree-sauna-dennenmarken-1-uur-padel-korting/d909df.jpg"
    },
    {
      "id": 43,
      "campaignID": 26224,
      "wellnessName": "Centre Du Lac",
      "title": "Dagentree Centre du Lac",
      "url": "https://www.tripper.nl/trips/?tt=26224_1169772_228134_&r=https%3A%2F%2Fwww.tripper.nl%2Fdeal%2Ftickets-centre-du-lac-korting",
      "oldPrice": 38,
      "newPrice": 27.95,
      "discount": 26,
      "image": "https://tripper.imgix.net/tickets-centre-du-lac-korting/5d7213.jpg"
    },
    {
      "id": 44,
      "campaignID": 26224,
      "wellnessName": "Wellness Center De Bronsbergen",
      "title": "Dagentree Wellness Center de Bronsbergen",
      "url": "https://www.tripper.nl/trips/?tt=26224_1169772_228134_&r=https%3A%2F%2Fwww.tripper.nl%2Fdeal%2Fdagentree-wellness-center-de-bronsbergen-korting",
      "oldPrice": 37.5,
      "newPrice": 26.5,
      "discount": 29,
      "image": "https://tripper.imgix.net/dagentree-wellness-center-de-bronsbergen-korting/9cda92.jpg"
    },
    {
      "id": 45,
      "campaignID": 26224,
      "wellnessName": "Spavarin",
      "title": "Dagentree Cityspa Spavarin + arrangement",
      "url": "https://www.tripper.nl/trips/?tt=26224_1169772_228134_&r=https%3A%2F%2Fwww.tripper.nl%2Fdeal%2Fentree-dag-cityspa-spavarin-arrangement-korting",
      "oldPrice": 25,
      "newPrice": 19.5,
      "discount": 22,
      "image": "https://tripper.imgix.net/entree-dag-cityspa-spavarin-arrangement-korting/b2e38b.jpg"
    },
    {
      "id": 46,
      "campaignID": 2301,
      "wellnessName": "Wellness Helmond",
      "title": "Fletcher Wellness-Hotel Helmond",
      "url": "https://www.zoweg.nl/tradetracker/?tt=2301_750467_228134_&r=https%3A%2F%2Fwww.zoweg.nl%2Fhotels%2Fnl%2Fhotel-helmond%2Ffletcher-wellness-hotel-helmond%2F",
      "oldPrice": null,
      "newPrice": 99,
      "discount": null,
      "image": "https://www.zoweg.nl/getimage/accommodations/202108/212/159/328_104459.jpg",
      "location": ["Helmond"]
    },
    {
      "id": 47,
      "campaignID": 13048,
      "title": "Saunatopia - Toegang voor twee personen",
      "url": "https://lt45.net/c/?si=13048&li=1685001&wi=244044&pid=b41d16aec5772420049e06393627b350&dl=product%2Fsaunatopia&ws=",
      "oldPrice": 66,
      "newPrice": 44,
      "discount": 33,
      "image": "https://media.graphassets.com/i8FurIHySQKlodWF3ZXC",
      "location": ""
    },
    {
      "id": 48,
      "campaignID": 13048,
      "wellnessName": "Spasense",
      "title": "Dagje wellness bij SpaSense",
      "url": "https://lt45.net/c/?si=13048&li=1685001&wi=244044&pid=ac5e409841b3dd4747da3ea2afb0f88f&dl=product%2Fwellness-spasense&ws=",
      "oldPrice": 39.5,
      "newPrice": 24.7,
      "discount": 37,
      "image": "https://media.graphassets.com/OnUUQst8QCSVP1nI1TNm",
      "location": ""
    },
    {
      "id": 49,
      "campaignID": 13048,
      "wellnessName": "Spa Wellness Weesp",
      "title": "Dagje wellness bij SpaWeesp",
      "url": "https://lt45.net/c/?si=13048&li=1685001&wi=244044&pid=ef6cfc89366e77058d64fb75b90370df&dl=product%2Fwellness-spaweesp&ws=",
      "oldPrice": 38.5,
      "newPrice": 22.2,
      "discount": 42,
      "image": "https://media.graphassets.com/uV7wKRNTD2aRfluZlrvg",
      "location": ""
    },
    {
      "id": 50,
      "campaignID": 13048,
      "wellnessName": "Spapuur",
      "title": "Dagje wellness bij SpaPuur",
      "url": "https://lt45.net/c/?si=13048&li=1685001&wi=244044&pid=cd8e41802d9e35c7e2625a1a86ff9462&dl=product%2Fwellness-spapuur&ws=",
      "oldPrice": 34.5,
      "newPrice": 20,
      "discount": 42,
      "image": "https://media.graphassets.com/RQ01s3j0QQGU4dtWWKxE",
      "location": ""
    },
    {
      "id": 51,
      "campaignID": 13048,
      "wellnessName": "Thermen Holiday",
      "title": "Dagje wellness bij Thermen Holiday",
      "url": "https://lt45.net/c/?si=13048&li=1685001&wi=244044&pid=26b1b66ec04afc699627507dba741b61&dl=product%2Fwellness-thermenholiday&ws=",
      "oldPrice": 38.52,
      "newPrice": 22.2,
      "discount": 42,
      "image": "https://media.graphassets.com/CDGo857PTpOQi5kEDjwt",
      "location": ""
    },
    {
      "id": 52,
      "campaignID": 13048,
      "wellnessName": "Body Home",
      "title": "Goodbye Stress Home&Body Pakket",
      "url": "https://lt45.net/c/?si=13048&li=1685001&wi=244044&pid=99474f4fbb565b52a1fb07bf8940ee18&dl=product%2Fgoodbye-stress-home-body-pakket&ws=",
      "oldPrice": 49.95,
      "newPrice": 27.95,
      "discount": 44,
      "image": "https://media.graphassets.com/q7QMkJN4TRrqdZ5CZSQZ",
      "location": ""
    },
    {
      "id": 53,
      "campaignID": 13048,
      "wellnessName": "Zwaluwhoeve",
      "title": "Dagje wellness bij Zwaluwhoeve",
      "url": "https://lt45.net/c/?si=13048&li=1685001&wi=244044&pid=f59f147ef7c72fa6c7071281b35ff86c&dl=product%2Fzwaluwhoeve&ws=",
      "oldPrice": 38.5,
      "newPrice": 22.2,
      "discount": 42,
      "image": "https://media.graphassets.com/88KGDGmS1KDTYRTN3xw8",
      "location": ""
    },
    {
      "id": 54,
      "campaignID": 13048,
      "wellnessName": "Veluwse Bron",
      "title": "Dagje wellness bij Veluwse Bron",
      "url": "https://lt45.net/c/?si=13048&li=1685001&wi=244044&pid=d63c9950dbe555a7a293dd1f7af127af&dl=product%2Fwellness-veluwsebron&ws=",
      "oldPrice": 42.5,
      "newPrice": 26.5,
      "discount": 38,
      "image": "https://media.graphassets.com/ZWjrmxMQ3GM98y0RZIQw",
      "location": ""
    },
    {
      "id": 55,
      "campaignID": 13048,
      "title": "Jugendstil-paddenstoellamp'Berlin'",
      "url": "https://lt45.net/c/?si=13048&li=1685001&wi=244044&pid=c5c46550494775f33a0620d7d9fb06c0&dl=product%2Fjugendstil-paddenstoellamp-berlin&ws=",
      "oldPrice": 0,
      "newPrice": 305,
      "discount": null,
      "image": "https://media.graphassets.com/9bnFerfIQNS0WWAAMxPe",
      "location": ""
    },
    {
      "id": 56,
      "campaignID": 13048,
      "wellnessName": "Elysium",
      "title": "Dagje wellness bij Elysium",
      "url": "https://lt45.net/c/?si=13048&li=1685001&wi=244044&pid=eefd0c9287030f39f487bbe445fe6fe3&dl=product%2Fdagje-wellness-elysium&ws=",
      "oldPrice": 42.5,
      "newPrice": 26.5,
      "discount": 38,
      "image": "https://media.graphassets.com/8qQ1Fp5SS3Wz7ZvZDbjE",
      "location": ""
    },
    {
      "id": 57,
      "campaignID": 686,
      "wellnessName": "Sanadome",
      "title": "Sanadome Hotel & Spa",
      "url": "https://www.hotelspecials.nl/hotel/?tt=686_344304_228134_&r=https%3A%2F%2Fwww.hotelspecials.nl%2Fh%2F19144.html%3Futm_source%3Dtradetracker",
      "oldPrice": null,
      "newPrice": 190,
      "discount": null,
      "image": "https://media.bookerzzz.com/1e63ecc7d94461b9486a94eb3fab35ee.jpeg",
      "location": ["Nijmegen"]
    },
    {
      "id": 58,
      "campaignID": 686,
      "wellnessName": "Spa Wellness Chateau St Gerlach",
      "title": "Chateau St. Gerlach",
      "url": "https://www.hotelspecials.nl/hotel/?tt=686_344304_228134_&r=https%3A%2F%2Fwww.hotelspecials.nl%2Fh%2F334.html%3Futm_source%3Dtradetracker",
      "oldPrice": null,
      "newPrice": 269,
      "discount": null,
      "image": "https://media.bookerzzz.com/2911121ab8a6d0f5d77e5ce0b7d4595b.jpeg",
      "location": ["Valkenburg"]
    },
    {
      "id": 59,
      "campaignID": 686,
      "wellnessName": "Bad Boekelo",
      "title": "Resort Bad Boekelo",
      "url": "https://www.hotelspecials.nl/hotel/?tt=686_344304_228134_&r=https%3A%2F%2Fwww.hotelspecials.nl%2Fh%2F188.html%3Futm_source%3Dtradetracker",
      "oldPrice": null,
      "newPrice": 100.33,
      "discount": null,
      "image": "https://media.bookerzzz.com/03c32b3b55c7fccc182339b3e89e097a.jpeg",
      "location": ["Boekelo"]
    },
    {
      "id": 60,
      "campaignID": 686,
      "wellnessName": "Landgoed De Rosep",
      "title": "Landgoed de Rosep",
      "url": "https://www.hotelspecials.nl/hotel/?tt=686_344304_228134_&r=https%3A%2F%2Fwww.hotelspecials.nl%2Fh%2F399.html%3Futm_source%3Dtradetracker",
      "oldPrice": null,
      "newPrice": 126,
      "discount": null,
      "image": "https://media.bookerzzz.com/5f36a020ac8c3068cf4763d16f0caf11.jpeg",
      "location": ["Oisterwijk"]
    },
    {
      "id": 61,
      "campaignID": 686,
      "wellnessName": "Thermen Bussloo",
      "title": "Wellness & Hotel Thermen Bussloo",
      "url": "https://www.hotelspecials.nl/hotel/?tt=686_344304_228134_&r=https%3A%2F%2Fwww.hotelspecials.nl%2Fh%2F7697.html%3Futm_source%3Dtradetracker",
      "oldPrice": null,
      "newPrice": 270,
      "discount": null,
      "image": "https://media.bookerzzz.com/75158158a22f13966e9dcf07398f2830.jpeg",
      "location": ["Bussloo"]
    },
    {
      "id": 62,
      "campaignID": 686,
      "wellnessName": "Zuiver Amsterdam",
      "title": "Hotel & Wellness Zuiver",
      "url": "https://www.hotelspecials.nl/hotel/?tt=686_344304_228134_&r=https%3A%2F%2Fwww.hotelspecials.nl%2Fh%2F6564.html%3Futm_source%3Dtradetracker",
      "oldPrice": null,
      "newPrice": 180,
      "discount": null,
      "image": "https://media.bookerzzz.com/72bbf516972e152d2e939eda14d4ce76.jpeg",
      "location": ["Amsterdam"]
    },
    {
      "id": 63,
      "campaignID": 686,
      "wellnessName": "Spavarin",
      "title": "Restaurant, Hotel & Spa Savarin",
      "url": "https://www.hotelspecials.nl/hotel/?tt=686_344304_228134_&r=https%3A%2F%2Fwww.hotelspecials.nl%2Fh%2F6126.html%3Futm_source%3Dtradetracker",
      "oldPrice": null,
      "newPrice": 159,
      "discount": null,
      "image": "https://media.bookerzzz.com/32afea84d2375cc8e05668e5e28d2938.jpeg",
      "location": ["Rijswijk"]
    }
  ]
  